{
  "date": "26 JUIN 2026",
  "headlines": [
    {
      "tag": "FOOT",
      "text": "Équateur élimine l'Allemagne 2-1",
      "hl": "2-1"
    },
    {
      "tag": "NBA",
      "text": "LaMelo Ball rejoint les Timberwolves",
      "hl": "TRADE"
    },
    {
      "tag": "LNH",
      "text": "Robertson refuse l'offre du Kraken",
      "hl": "REFUS"
    },
    {
      "tag": "QC",
      "text": "Gallagher citoyen d'honneur de MTL",
      "hl": "19 ANS"
    },
    {
      "tag": "F1",
      "text": "Hamilton chasse Antonelli en Autriche",
      "hl": "RATTRAPAGE"
    }
  ]
}